odoo/addons/account_financial_report_operating_unit/README.rst
odoo/addons/account_financial_report_operating_unit/__init__.py
odoo/addons/account_financial_report_operating_unit/__manifest__.py
odoo/addons/account_financial_report_operating_unit/i18n/account_financial_report_operating_unit.pot
odoo/addons/account_financial_report_operating_unit/readme/CONTRIBUTORS.rst
odoo/addons/account_financial_report_operating_unit/readme/DESCRIPTION.rst
odoo/addons/account_financial_report_operating_unit/report/__init__.py
odoo/addons/account_financial_report_operating_unit/report/aged_partner_balance.py
odoo/addons/account_financial_report_operating_unit/report/general_ledger.py
odoo/addons/account_financial_report_operating_unit/report/journal_ledger.py
odoo/addons/account_financial_report_operating_unit/report/open_items.py
odoo/addons/account_financial_report_operating_unit/report/trial_balance.py
odoo/addons/account_financial_report_operating_unit/report/vat_report.py
odoo/addons/account_financial_report_operating_unit/static/description/icon.png
odoo/addons/account_financial_report_operating_unit/static/description/index.html
odoo/addons/account_financial_report_operating_unit/wizards/__init__.py
odoo/addons/account_financial_report_operating_unit/wizards/aged_partner_balance_wizard.py
odoo/addons/account_financial_report_operating_unit/wizards/aged_partner_balance_wizard_view.xml
odoo/addons/account_financial_report_operating_unit/wizards/general_ledger_wizard.py
odoo/addons/account_financial_report_operating_unit/wizards/general_ledger_wizard_view.xml
odoo/addons/account_financial_report_operating_unit/wizards/journal_ledger_wizard.py
odoo/addons/account_financial_report_operating_unit/wizards/journal_ledger_wizard_view.xml
odoo/addons/account_financial_report_operating_unit/wizards/open_items_wizard.py
odoo/addons/account_financial_report_operating_unit/wizards/open_items_wizard_view.xml
odoo14_addon_account_financial_report_operating_unit-14.0.1.0.2.dist-info/METADATA
odoo14_addon_account_financial_report_operating_unit-14.0.1.0.2.dist-info/WHEEL
odoo14_addon_account_financial_report_operating_unit-14.0.1.0.2.dist-info/top_level.txt
odoo14_addon_account_financial_report_operating_unit-14.0.1.0.2.dist-info/RECORD
